Metadata-Version: 2.1
Name: odoo14-addon-sale_blanket_order_revision
Version: 14.0.1.0.1.dev8
Summary: Revision feture for Blanket Orders
Home-page: https://github.com/OCA/sale-workflow
Author: PyTech-SRL, Odoo Community Association (OCA)
Author-email: support@odoo-community.org
License: AGPL-3
Classifier: Programming Language :: Python
Classifier: Framework :: Odoo
Classifier: Framework :: Odoo :: 14.0
Classifier: License :: OSI Approved :: GNU Affero General Public License v3
Requires-Python: >=3.6
Requires-Dist: odoo14-addon-base-revision
Requires-Dist: odoo14-addon-sale-blanket-order
Requires-Dist: odoo<14.1dev,>=14.0a
